docxparsr/__init__.py
docxparsr/parsr/__init__.py
docxparsr/parsr/buildr.py
docxparsr-0.1.8.dist-info/METADATA
docxparsr-0.1.8.dist-info/WHEEL
docxparsr-0.1.8.dist-info/RECORD
