Metadata-Version: 2.1
Name: docxparsr
Version: 0.1.8
Summary: Parse docx files
License: MIT
Author: Polyhedron
Requires-Python: >=3.10,<4.0
Classifier: License :: OSI Approved :: MIT License
Classifier: Programming Language :: Python :: 3
Classifier: Programming Language :: Python :: 3.10
Classifier: Programming Language :: Python :: 3.11
Requires-Dist: lxml (>=4.9.3,<5.0.0)
